apodeflags/__init__.py
apodeflags/adapter.py
apodeflags/errors.py
apodeflags/features.py
apodeflags/utils.py
apodeflags-0.0.2.dist-info/METADATA
apodeflags-0.0.2.dist-info/RECORD
apodeflags-0.0.2.dist-info/WHEEL
apodeflags-0.0.2.dist-info/top_level.txt
tests/__init__.py
tests/test_feature.py
