Metadata-Version: 2.1
Name: apodeflags
Version: 0.0.2
Summary: Simple feature flag configuration
Home-page: https://github.com/apode-io/apodeflags
Author: Felix Panozzo
Author-email: felix@apode.se
License: UNKNOWN
Platform: UNKNOWN
Classifier: Programming Language :: Python :: 3
Classifier: License :: OSI Approved :: MIT License
Classifier: Operating System :: OS Independent
Classifier: Development Status :: 3 - Alpha
Classifier: Intended Audience :: Developers
